setupcode/__init__.py
setupcode/notebook.py
setupcode-1.1.dist-info/METADATA
setupcode-1.1.dist-info/WHEEL
setupcode-1.1.dist-info/licenses/LICENSE
setupcode-1.1.dist-info/RECORD
