Metadata-Version: 2.1
Name: setupcode
Version: 1.1
Summary: setup configs settings snippets
License-Expression: MIT
License-File: LICENSE
Keywords: configs,settings,setup,snippets
Requires-Python: >=3.7
